castle/__init__.py
castle/aot/__init__.py
castle/aot/configs/__init__.py
castle/aot/configs/default.py
castle/aot/configs/pre.py
castle/aot/configs/pre_dav.py
castle/aot/configs/pre_ytb.py
castle/aot/configs/pre_ytb_dav.py
castle/aot/configs/ytb.py
castle/aot/configs/models/__init__.py
castle/aot/configs/models/aotb.py
castle/aot/configs/models/aotl.py
castle/aot/configs/models/aots.py
castle/aot/configs/models/aott.py
castle/aot/configs/models/deaotb.py
castle/aot/configs/models/deaotl.py
castle/aot/configs/models/deaots.py
castle/aot/configs/models/deaott.py
castle/aot/configs/models/default.py
castle/aot/configs/models/default_deaot.py
castle/aot/configs/models/r101_aotl.py
castle/aot/configs/models/r50_aotl.py
castle/aot/configs/models/r50_deaotl.py
castle/aot/configs/models/rs101_aotl.py
castle/aot/configs/models/swinb_aotl.py
castle/aot/configs/models/swinb_deaotl.py
castle/aot/dataloaders/__init__.py
castle/aot/dataloaders/eval_datasets.py
castle/aot/dataloaders/image_transforms.py
castle/aot/dataloaders/train_datasets.py
castle/aot/dataloaders/video_transforms.py
castle/aot/networks/__init__.py
castle/aot/networks/decoders/__init__.py
castle/aot/networks/decoders/fpn.py
castle/aot/networks/encoders/__init__.py
castle/aot/networks/encoders/mobilenetv2.py
castle/aot/networks/encoders/mobilenetv3.py
castle/aot/networks/encoders/resnet.py
castle/aot/networks/encoders/resnest/__init__.py
castle/aot/networks/encoders/resnest/resnest.py
castle/aot/networks/encoders/resnest/resnet.py
castle/aot/networks/encoders/resnest/splat.py
castle/aot/networks/encoders/swin/__init__.py
castle/aot/networks/encoders/swin/build.py
castle/aot/networks/encoders/swin/swin_transformer.py
castle/aot/networks/engines/__init__.py
castle/aot/networks/engines/aot_engine.py
castle/aot/networks/engines/deaot_engine.py
castle/aot/networks/layers/__init__.py
castle/aot/networks/layers/attention.py
castle/aot/networks/layers/basic.py
castle/aot/networks/layers/loss.py
castle_ai-0.0.15.dist-info/LICENSE.txt
castle_ai-0.0.15.dist-info/METADATA
castle_ai-0.0.15.dist-info/WHEEL
castle_ai-0.0.15.dist-info/top_level.txt
castle_ai-0.0.15.dist-info/RECORD
