Metadata-Version: 2.2
Name: castle-ai
Version: 0.0.15
Summary: Distinguish behavioral clusters Toolbox
Maintainer: Raiso Liu
Maintainer-email: rainsoon717@gmail.com
License: AGPL-3.0 license
Classifier: Development Status :: 1 - Planning
Classifier: Intended Audience :: Science/Research
Classifier: Intended Audience :: Developers
Classifier: Programming Language :: Python
Classifier: Topic :: Scientific/Engineering
Classifier: Operating System :: Microsoft :: Windows
Classifier: Operating System :: Unix
Classifier: Operating System :: MacOS
Classifier: Programming Language :: Python :: 3
License-File: LICENSE.txt
Dynamic: classifier
Dynamic: description
Dynamic: description-content-type
Dynamic: license
Dynamic: maintainer
Dynamic: maintainer-email
Dynamic: summary
